mixins/__init__.py
mixins/crud.py
mixins/orderable.py
mixins/session.py
tests/__init__.py
tests/test_crud.py
tests/test_oderable.py
tests/test_real_db.py
tests/test_session.py
py_sqlalchemy_mixins-0.0.1.dist-info/METADATA
py_sqlalchemy_mixins-0.0.1.dist-info/WHEEL
py_sqlalchemy_mixins-0.0.1.dist-info/top_level.txt
py_sqlalchemy_mixins-0.0.1.dist-info/RECORD
